lekko_client/__init__.py
lekko_client/constants.py
lekko_client/exceptions.py
lekko_client/helpers.py
lekko_client/models.py
lekko_client/clients/__init__.py
lekko_client/clients/cached_backend_client.py
lekko_client/clients/cached_git_client.py
lekko_client/clients/client.py
lekko_client/clients/config_client.py
lekko_client/clients/distribution_client.py
lekko_client/evaluation/evaluation.py
lekko_client/evaluation/rules.py
lekko_client/gen/lekko/backend/v1beta1/distribution_service_pb2.py
lekko_client/gen/lekko/backend/v1beta1/distribution_service_pb2.pyi
lekko_client/gen/lekko/backend/v1beta1/distribution_service_pb2_grpc.py
lekko_client/gen/lekko/backend/v1beta1/distribution_service_pb2_grpc.pyi
lekko_client/gen/lekko/client/v1beta1/configuration_service_pb2.py
lekko_client/gen/lekko/client/v1beta1/configuration_service_pb2.pyi
lekko_client/gen/lekko/client/v1beta1/configuration_service_pb2_grpc.py
lekko_client/gen/lekko/client/v1beta1/configuration_service_pb2_grpc.pyi
lekko_client/gen/lekko/feature/v1beta1/feature_pb2.py
lekko_client/gen/lekko/feature/v1beta1/feature_pb2.pyi
lekko_client/gen/lekko/feature/v1beta1/feature_pb2_grpc.py
lekko_client/gen/lekko/feature/v1beta1/feature_pb2_grpc.pyi
lekko_client/gen/lekko/feature/v1beta1/static_pb2.py
lekko_client/gen/lekko/feature/v1beta1/static_pb2.pyi
lekko_client/gen/lekko/feature/v1beta1/static_pb2_grpc.py
lekko_client/gen/lekko/feature/v1beta1/static_pb2_grpc.pyi
lekko_client/gen/lekko/rules/v1beta2/rules_pb2.py
lekko_client/gen/lekko/rules/v1beta2/rules_pb2.pyi
lekko_client/gen/lekko/rules/v1beta2/rules_pb2_grpc.py
lekko_client/gen/lekko/rules/v1beta2/rules_pb2_grpc.pyi
lekko_client/gen/lekko/rules/v1beta3/rules_pb2.py
lekko_client/gen/lekko/rules/v1beta3/rules_pb2.pyi
lekko_client/gen/lekko/rules/v1beta3/rules_pb2_grpc.py
lekko_client/gen/lekko/rules/v1beta3/rules_pb2_grpc.pyi
lekko_client/stores/memory.py
lekko_client/stores/store.py
lekko_client-0.2.1.dist-info/LICENSE
lekko_client-0.2.1.dist-info/WHEEL
lekko_client-0.2.1.dist-info/METADATA
lekko_client-0.2.1.dist-info/RECORD
